kion_mcp/__init__.py
kion_mcp/exceptions.py
kion_mcp/fixed_spec.json
kion_mcp/server.py
kion_mcp/clients/__init__.py
kion_mcp/clients/kion_client.py
kion_mcp/config/__init__.py
kion_mcp/config/auth.py
kion_mcp/config/settings.py
kion_mcp/constants/tools.py
kion_mcp/interaction/__init__.py
kion_mcp/interaction/elicitation.py
kion_mcp/middleware/__init__.py
kion_mcp/middleware/auth.py
kion_mcp/middleware/financial.py
kion_mcp/parsers/__init__.py
kion_mcp/parsers/spend_report.py
kion_mcp/server_management/__init__.py
kion_mcp/server_management/routes.py
kion_mcp/server_management/tool_manager.py
kion_mcp/tools/__init__.py
kion_mcp/tools/cloud_access_role_tools.py
kion_mcp/tools/config_tool.py
kion_mcp/tools/custom_tools.py
kion_mcp/tools/entity_tools.py
kion_mcp/tools/label_tools.py
kion_mcp/tools/spend_report.py
kion_mcp/tools/user_info.py
kion_mcp/utils/__init__.py
kion_mcp/utils/dxt.py
kion_mcp/utils/http_helper.py
kion_mcp/utils/route_generator.py
kion_mcp/utils/spec_loader.py
kion_mcp_server-0.3.0.dist-info/METADATA
kion_mcp_server-0.3.0.dist-info/WHEEL
kion_mcp_server-0.3.0.dist-info/entry_points.txt
kion_mcp_server-0.3.0.dist-info/licenses/LICENSE
kion_mcp_server-0.3.0.dist-info/RECORD
