Metadata-Version: 2.4
Name: kion-mcp-server
Version: 0.3.0
Summary: Kion MCP Server - Model Context Protocol server for Kion API integration
Project-URL: Homepage, https://github.com/kionsoftware/kion-mcp
Project-URL: Repository, https://github.com/kionsoftware/kion-mcp
Project-URL: Issues, https://github.com/kionsoftware/kion-mcp/issues
Project-URL: Documentation, https://github.com/kionsoftware/kion-mcp/blob/main/README.md
Author-email: Kion Software <support@kion.io>
Maintainer-email: Kion Software <support@kion.io>
License: MIT License
License-File: LICENSE
Keywords: api,cloud,governance,kion,mcp
Classifier: Development Status :: 4 - Beta
Classifier: Intended Audience :: Developers
Classifier: Intended Audience :: System Administrators
Classifier: License :: OSI Approved :: MIT License
Classifier: Operating System :: OS Independent
Classifier: Programming Language :: Python :: 3
Classifier: Programming Language :: Python :: 3.13
Classifier: Topic :: Software Development :: Libraries :: Python Modules
Classifier: Topic :: System :: Systems Administration
Requires-Python: >=3.13
Requires-Dist: fastmcp>=2.10.5
Requires-Dist: httpx>=0.28.1
Requires-Dist: pyyaml>=6.0.2
